{
  "timestamp": "2025-10-28T12:36:49.654Z",
  "request": {
    "url": "https://estacionpago.ehub.com.gt/recargas.svc/ObtieneOperadorTelefono",
    "body": {
      "telefono": "54882456"
    },
    "headers": {
      "host": "localhost:3001",
      "connection": "close",
      "content-length": "23",
      "sec-ch-ua-platform": "\"Windows\"",
      "user-agent": "Mozilla/5.0 (Windows NT 10.0; Win64; x64) AppleWebKit/537.36 (KHTML, like Gecko) Chrome/141.0.0.0 Safari/537.36",
      "sec-ch-ua": "\"Google Chrome\";v=\"141\", \"Not?A_Brand\";v=\"8\", \"Chromium\";v=\"141\"",
      "dnt": "1",
      "content-type": "application/json",
      "sec-ch-ua-mobile": "?0",
      "accept": "*/*",
      "origin": "http://localhost:5173",
      "sec-fetch-site": "same-origin",
      "sec-fetch-mode": "cors",
      "sec-fetch-dest": "empty",
      "referer": "http://localhost:5173/recarga",
      "accept-encoding": "gzip, deflate, br, zstd",
      "accept-language": "es-ES,es;q=0.9,en;q=0.8,zh-CN;q=0.7,zh;q=0.6"
    }
  },
  "response": {
    "status": 200,
    "body": 1
  }
}